Metadata-Version: 2.1
Name: telebase
Version: 1.0.1
Summary: Telebase é um projeto de código aberto que visa a criação de um sistema de gerenciamento de dados json para o Telegram.
Home-page: https://github.com/marcellobatiista/Telebase
Author: Marcelo Batista
Author-email: batista.marcelo34@gmail.com
License: MIT
Keywords: telegram chat messenger api db json database crud library python
Requires-Python: >=3.7
License-File: LICENSE
